modelcatalog/__init__.py
modelcatalog/api_client.py
modelcatalog/configuration.py
modelcatalog/exceptions.py
modelcatalog/rest.py
modelcatalog/api/__init__.py
modelcatalog/api/catalog_identifier_api.py
modelcatalog/api/causal_diagram_api.py
modelcatalog/api/configuration_setup_api.py
modelcatalog/api/coupled_model_api.py
modelcatalog/api/data_transformation_api.py
modelcatalog/api/data_transformation_setup_api.py
modelcatalog/api/dataset_specification_api.py
modelcatalog/api/default_api.py
modelcatalog/api/empirical_model_api.py
modelcatalog/api/emulator_api.py
modelcatalog/api/equation_api.py
modelcatalog/api/funding_information_api.py
modelcatalog/api/geo_coordinates_api.py
modelcatalog/api/geo_shape_api.py
modelcatalog/api/grid_api.py
modelcatalog/api/hybrid_model_api.py
modelcatalog/api/image_api.py
modelcatalog/api/intervention_api.py
modelcatalog/api/model_api.py
modelcatalog/api/model_category_api.py
modelcatalog/api/model_configuration_api.py
modelcatalog/api/model_configuration_setup_api.py
modelcatalog/api/numerical_index_api.py
modelcatalog/api/organization_api.py
modelcatalog/api/parameter_api.py
modelcatalog/api/person_api.py
modelcatalog/api/point_based_grid_api.py
modelcatalog/api/process_api.py
modelcatalog/api/region_api.py
modelcatalog/api/sample_collection_api.py
modelcatalog/api/sample_execution_api.py
modelcatalog/api/sample_resource_api.py
modelcatalog/api/software_api.py
modelcatalog/api/software_configuration_api.py
modelcatalog/api/software_image_api.py
modelcatalog/api/software_version_api.py
modelcatalog/api/source_code_api.py
modelcatalog/api/spatial_resolution_api.py
modelcatalog/api/spatially_distributed_grid_api.py
modelcatalog/api/standard_variable_api.py
modelcatalog/api/theory_guided_model_api.py
modelcatalog/api/time_interval_api.py
modelcatalog/api/unit_api.py
modelcatalog/api/variable_api.py
modelcatalog/api/variable_presentation_api.py
modelcatalog/api/visualization_api.py
modelcatalog/models/__init__.py
modelcatalog_api-7.0.0.dist-info/METADATA
modelcatalog_api-7.0.0.dist-info/WHEEL
modelcatalog_api-7.0.0.dist-info/top_level.txt
modelcatalog_api-7.0.0.dist-info/RECORD
