Metadata-Version: 1.0
Name: modelcatalog-api
Version: 7.0.0
Summary: Model Catalog
Home-page: https://pypi.org/project/modelcatalog-api/
Author: UNKNOWN
Author-email: UNKNOWN
License: UNKNOWN
Keywords: OpenAPI,OpenAPI-Generator,Model Catalog
Platform: UNKNOWN
